Metadata-Version: 2.1
Name: datasette-enrichments-quickjs
Version: 0.1a2
Summary: Enrich data with a custom JavaScript function
Author: Simon Willison
License: Apache-2.0
Project-URL: Homepage, https://github.com/datasette/datasette-enrichments-quickjs
Project-URL: Changelog, https://github.com/datasette/datasette-enrichments-quickjs/releases
Project-URL: Issues, https://github.com/datasette/datasette-enrichments-quickjs/issues
Project-URL: CI, https://github.com/datasette/datasette-enrichments-quickjs/actions
Classifier: Framework :: Datasette
Classifier: License :: OSI Approved :: Apache Software License
Requires-Python: >=3.8
License-File: LICENSE
Requires-Dist: datasette
Requires-Dist: datasette-enrichments
Requires-Dist: quickjs
Requires-Dist: sqlite-utils
Provides-Extra: test
Requires-Dist: pytest ; extra == 'test'
Requires-Dist: pytest-asyncio ; extra == 'test'
Requires-Dist: pytest-timeout ; extra == 'test'
